[
    {
        "iconUrl": "https://cdn.discordapp.com/attachments/1109266606292488297/1200425504432472176/Anichi.png?ex=65eb0c5f&is=65d8975f&hm=974898b22b08774a5caa835b40546a6419280446b68255147dd1febb3abe9119&",
        "apiVersion": 1,
        "repositoryUrl": "https://github.com/hexated/cloudstream-extensions-hexated",
        "fileSize": 55347,
        "status": 1,
        "language": "en",
        "authors": [
            "Hexated"
        ],
        "tvTypes": [
            "AnimeMovie",
            "Anime",
            "OVA"
        ],
        "version": 10,
        "internalName": "Anichi",
        "url": "https://raw.githubusercontent.com/hexated/cloudstream-extensions-hexated/builds/Anichi.cs3",
        "name": "Anichi"
    },
    {
        "iconUrl": "https://raw.githubusercontent.com/phisher98/TVVVV/refs/heads/main/Icons/daddylive.png",
        "apiVersion": 1,
        "repositoryUrl": "https://github.com/phisher98/cloudstream-extensions-phisher",
        "fileSize": 21644,
        "status": 1,
        "authors": [
            "Phisher98"
        ],
        "tvTypes": [
            "Live"
        ],
        "version": 6,
        "internalName": "DaddyLive",
        "description": "Live & Sport TV",
        "url": "https://raw.githubusercontent.com/phisher98/cloudstream-extensions-phisher/builds/DaddyLive.cs3",
        "name": "DaddyLive"
    },
    {
        "iconUrl": "https://www.google.com/s2/favicons?domain=www.dubbindo.xyz&sz=%size%",
        "apiVersion": 1,
        "repositoryUrl": "https://github.com/hexated/cloudstream-extensions-hexated",
        "fileSize": 12041,
        "status": 1,
        "language": "id",
        "authors": [
            "Hexated"
        ],
        "tvTypes": [
            "TvSeries",
            "Movie",
            "Cartoon",
            "Anime"
        ],
        "version": 1,
        "internalName": "Dubbindo",
        "url": "https://raw.githubusercontent.com/hexated/cloudstream-extensions-hexated/builds/Dubbindo.cs3",
        "name": "Dubbindo"
    },
    {
        "iconUrl": "https://www.google.com/s2/favicons?domain=amp.lk21official.mom&sz=%size%",
        "apiVersion": 1,
        "repositoryUrl": "https://github.com/hexated/cloudstream-extensions-hexated",
        "fileSize": 19301,
        "status": 1,
        "language": "id",
        "authors": [
            "Hexated"
        ],
        "tvTypes": [
            "AsianDrama",
            "TvSeries",
            "Movie"
        ],
        "version": 20,
        "internalName": "LayarKacaProvider",
        "url": "https://raw.githubusercontent.com/hexated/cloudstream-extensions-hexated/builds/LayarKacaProvider.cs3",
        "name": "LayarKacaProvider"
    },
    {
        "iconUrl": "https://github.com/SaurabhKaperwan/CSX/raw/refs/heads/master/NetflixMirrorProvider/icon.png",
        "apiVersion": 1,
        "repositoryUrl": "https://github.com/SaurabhKaperwan/CSX",
        "fileSize": 42583,
        "status": 1,
        "authors": [
            "megix"
        ],
        "tvTypes": [
            "Movie",
            "TvSeries"
        ],
        "version": 24,
        "internalName": "NetflixMirrorProvider",
        "description": "Netflix, PrimeVideo, Disney Hotstar Content in Multiple Languages",
        "url": "https://raw.githubusercontent.com/SaurabhKaperwan/CSX/builds/NetflixMirrorProvider.cs3",
        "name": "NetflixMirrorProvider"
    },
    {
        "iconUrl": "https://t2.gstatic.com/faviconV2?client=SOCIAL&type=FAVICON&fallback_opts=TYPE,SIZE,URL&url=https://ww03.pencurimovie.bond&size=%size%",
        "apiVersion": 1,
        "repositoryUrl": "https://github.com/TeKuma25/IndoStream",
        "fileSize": 12443,
        "status": 1,
        "language": "id",
        "authors": [
            "Phisher98"
        ],
        "tvTypes": [
            "Movie",
            "TvSeries"
        ],
        "version": 3,
        "internalName": "Pencurimovie",
        "description": "Pencurimovie ",
        "url": "https://raw.githubusercontent.com/TeKuma25/IndoStream/builds/Pencurimovie.cs3",
        "name": "Pencurimovie"
    },
    {
        "iconUrl": "https://i3.wp.com/yt3.googleusercontent.com/ytc/AIdro_nCBArSmvOc6o-k2hTYpLtQMPrKqGtAw_nC20rxm70akA=s900-c-k-c0x00ffffff-no-rj?ssl=1",
        "apiVersion": 1,
        "repositoryUrl": "https://github.com/phisher98/cloudstream-extensions-phisher",
        "fileSize": 763155,
        "status": 1,
        "language": "en",
        "authors": [
            "Phisher98",
            "Hexated"
        ],
        "tvTypes": [
            "AsianDrama",
            "TvSeries",
            "Anime",
            "Movie",
            "Cartoon",
            "AnimeMovie"
        ],
        "version": 376,
        "internalName": "StreamPlay",
        "description": "#1 best extention based on MultiAPI",
        "url": "https://raw.githubusercontent.com/phisher98/cloudstream-extensions-phisher/builds/StreamPlay.cs3",
        "name": "StreamPlay"
    },
    {
        "iconUrl": "https://cdn.discordapp.com/attachments/1109266606292488297/1193122096159674448/2-modified.png?ex=65ec2a0a&is=65d9b50a&hm=f1e0b0165e71101e5440b47592d9e15727a6c00cdeb3512108067bfbdbef1af7&",
        "apiVersion": 1,
        "repositoryUrl": "https://github.com/hexated/cloudstream-extensions-hexated",
        "fileSize": 275303,
        "status": 0,
        "language": "en",
        "authors": [
            "Hexated",
            "Sora"
        ],
        "tvTypes": [
            "AsianDrama",
            "TvSeries",
            "Anime",
            "Movie"
        ],
        "version": 228,
        "internalName": "SoraStream",
        "description": "#1 best extention based on MultiAPI",
        "url": "https://raw.githubusercontent.com/hexated/cloudstream-extensions-hexated/builds/SoraStream.cs3",
        "name": "SoraStream"
    }
]
